<?xml version="1.0" encoding="UTF-8"?>

<xwikidoc>
  <web>RecruitmentApp</web>
  <name>RecruitmentAppTranslations</name>
  <language/>
  <defaultLanguage/>
  <translation>0</translation>
  <parent>RecruitmentAppClass</parent>
  <creator>xwiki:XWiki.Admin</creator>
  <author>xwiki:XWiki.Admin</author>
  <customClass/>
  <contentAuthor>xwiki:XWiki.Admin</contentAuthor>
  <creationDate>1367311699000</creationDate>
  <date>1368523902000</date>
  <contentUpdateDate>1368523902000</contentUpdateDate>
  <version>1.1</version>
  <title/>
  <template/>
  <defaultTemplate/>
  <validationScript/>
  <comment/>
  <minorEdit>false</minorEdit>
  <syntaxId>xwiki/2.1</syntaxId>
  <hidden>true</hidden>
  <object>
    <class>
      <name>XWiki.TranslationDocumentClass</name>
      <customClass/>
      <customMapping/>
      <defaultViewSheet/>
      <defaultEditSheet/>
      <defaultWeb/>
      <nameField/>
      <validationScript/>
      <scope>
        <cache>0</cache>
        <disabled>0</disabled>
        <displayType>select</displayType>
        <multiSelect>0</multiSelect>
        <name>scope</name>
        <number>1</number>
        <prettyName>Scope</prettyName>
        <relationalStorage>0</relationalStorage>
        <separator> </separator>
        <separators> ,|</separators>
        <size>1</size>
        <unmodifiable>0</unmodifiable>
        <values>GLOBAL|WIKI|USER|ON_DEMAND</values>
        <classType>com.xpn.xwiki.objects.classes.StaticListClass</classType>
      </scope>
    </class>
    <name>RecruitmentApp.RecruitmentAppTranslations</name>
    <number>0</number>
    <className>XWiki.TranslationDocumentClass</className>
    <guid>e85a7319-c75e-4b76-aec1-19ba267f2138</guid>
    <property>
      <scope>ON_DEMAND</scope>
    </property>
  </object>
  <content># Class fields
RecruitmentApp.RecruitmentAppClass_first_name=First name
RecruitmentApp.RecruitmentAppClass_last_name=Last name
RecruitmentApp.RecruitmentAppClass_email=Email
RecruitmentApp.RecruitmentAppClass_skype=Skype
RecruitmentApp.RecruitmentAppClass_phone=Phone
RecruitmentApp.RecruitmentAppClass_office=Office
RecruitmentApp.RecruitmentAppClass_office_2=Iasi
RecruitmentApp.RecruitmentAppClass_office_1=Paris
RecruitmentApp.RecruitmentAppClass_department=Department
RecruitmentApp.RecruitmentAppClass_department_2=SysAdmin
RecruitmentApp.RecruitmentAppClass_department_1=Technology
RecruitmentApp.RecruitmentAppClass_status=Status
RecruitmentApp.RecruitmentAppClass_status_2=Accepted
RecruitmentApp.RecruitmentAppClass_status_1=None
RecruitmentApp.RecruitmentAppClass_rating=Rating
RecruitmentApp.RecruitmentAppClass_current_position=Current position
RecruitmentApp.RecruitmentAppClass_current_company=Current company
RecruitmentApp.RecruitmentAppClass_details=Details
RecruitmentApp.RecruitmentAppClass_next_steps=Next steps

# Live table generic keys
recruitmentapp.livetable.doc.title=Page title
recruitmentapp.livetable.doc.name=Page name
recruitmentapp.livetable.doc.space=Space
recruitmentapp.livetable.doc.fullname=Page full name
recruitmentapp.livetable.doc.author=Last Author
recruitmentapp.livetable.doc.creator=Creator
recruitmentapp.livetable.doc.date=Update date
recruitmentapp.livetable.doc.creationDate=Creation date
recruitmentapp.livetable._avatar=Avatar
recruitmentapp.livetable._images=Images
recruitmentapp.livetable._attachments=Attachments
recruitmentapp.livetable._actions=Actions
recruitmentapp.livetable._actions.edit=Edit
recruitmentapp.livetable._actions.delete=Delete
recruitmentapp.livetable.emptyvalue=-

# Live table specific keys
recruitmentapp.livetable.first_name=First name
recruitmentapp.livetable.last_name=Last name
recruitmentapp.livetable.email=Email
recruitmentapp.livetable.skype=Skype
recruitmentapp.livetable.phone=Phone
recruitmentapp.livetable.office=Office
recruitmentapp.livetable.department=Department
recruitmentapp.livetable.status=Status
recruitmentapp.livetable.sourceType=Source type
recruitmentapp.livetable.applyDate=Apply date
recruitmentapp.livetable.hiringDate=Hiring date
recruitmentapp.livetable.rating=Rating
recruitmentapp.livetable.current_position=Current position
recruitmentapp.livetable.current_company=Current company
recruitmentapp.livetable.details=Details
recruitmentapp.livetable.next_steps=Next steps
recruitmentapp.livetable.jobPosting=Job Posting

recruitmentapp.livetable.sourceChannel=Source Channel</content>
</xwikidoc>
